<?xml version="1.0" encoding="UTF-8"?>
<MF0 version="1.1" packageUris="http://schema.mathworks.com/mf0/sl_modelref_info/R2020a http://schema.mathworks.com/mf0/slexec_mm_sto/R2019b_201902271317">
  <ModelRefInfoRepo.ModelRefInfoRoot type="ModelRefInfoRepo.ModelRefInfoRoot" uuid="dbc194e6-e428-4e42-8649-828868ac9b9b">
    <autoSolverStatusFlags>327</autoSolverStatusFlags>
    <childModelRefInfo type="ModelRefInfoRepo.ChildModelRefInfo" uuid="e55db1d0-a512-42a0-816a-d2675f678d6a">
      <modelName>TST_RWSWV2</modelName>
      <modelPath>TST_RWSWV2</modelPath>
    </childModelRefInfo>
    <dataTransferInfos>AAFJTQAAAAAOAAAAOAAAAAYAAAAIAAAAAgAAAAAAAAAFAAAACAAAAAAAAAABAAAAAQAAAAAAAAAFAAQAAQAAAAEAAAAAAAAA</dataTransferInfos>
    <defaultsCMapping>{&quot;Inports&quot;:&quot;{\&quot;Name\&quot;:\&quot;Default\&quot;,\&quot;Checksum\&quot;:\&quot;Default\&quot;,\&quot;PerInstancePropertiesChecksum\&quot;:\&quot;\&quot;,\&quot;MemorySectionName\&quot;:\&quot;\&quot;,\&quot;MemorySectionChecksum\&quot;:\&quot;\&quot;}&quot;,&quot;Outports&quot;:&quot;{\&quot;Name\&quot;:\&quot;Default\&quot;,\&quot;Checksum\&quot;:\&quot;Default\&quot;,\&quot;PerInstancePropertiesChecksum\&quot;:\&quot;\&quot;,\&quot;MemorySectionName\&quot;:\&quot;\&quot;,\&quot;MemorySectionChecksum\&quot;:\&quot;\&quot;}&quot;,&quot;LocalParameters&quot;:&quot;{\&quot;Name\&quot;:\&quot;Default\&quot;,\&quot;Checksum\&quot;:\&quot;Default\&quot;,\&quot;PerInstancePropertiesChecksum\&quot;:\&quot;\&quot;,\&quot;MemorySectionName\&quot;:\&quot;\&quot;,\&quot;MemorySectionChecksum\&quot;:\&quot;\&quot;}&quot;,&quot;ParameterArguments&quot;:&quot;{\&quot;Name\&quot;:\&quot;Default\&quot;,\&quot;Checksum\&quot;:\&quot;Default\&quot;,\&quot;PerInstancePropertiesChecksum\&quot;:\&quot;\&quot;,\&quot;MemorySectionName\&quot;:\&quot;None\&quot;,\&quot;MemorySectionChecksum\&quot;:\&quot;None\&quot;}&quot;,&quot;GlobalParameters&quot;:&quot;{\&quot;Name\&quot;:\&quot;Default\&quot;,\&quot;Checksum\&quot;:\&quot;Default\&quot;,\&quot;PerInstancePropertiesChecksum\&quot;:\&quot;\&quot;,\&quot;MemorySectionName\&quot;:\&quot;\&quot;,\&quot;MemorySectionChecksum\&quot;:\&quot;\&quot;}&quot;,&quot;SharedLocalDataStores&quot;:&quot;{\&quot;Name\&quot;:\&quot;Default\&quot;,\&quot;Checksum\&quot;:\&quot;Default\&quot;,\&quot;PerInstancePropertiesChecksum\&quot;:\&quot;\&quot;,\&quot;MemorySectionName\&quot;:\&quot;None\&quot;,\&quot;MemorySectionChecksum\&quot;:\&quot;None\&quot;}&quot;,&quot;GlobalDataStores&quot;:&quot;{\&quot;Name\&quot;:\&quot;Default\&quot;,\&quot;Checksum\&quot;:\&quot;Default\&quot;,\&quot;PerInstancePropertiesChecksum\&quot;:\&quot;\&quot;,\&quot;MemorySectionName\&quot;:\&quot;None\&quot;,\&quot;MemorySectionChecksum\&quot;:\&quot;None\&quot;}&quot;,&quot;InternalData&quot;:&quot;{\&quot;Name\&quot;:\&quot;Default\&quot;,\&quot;Checksum\&quot;:\&quot;Default\&quot;,\&quot;PerInstancePropertiesChecksum\&quot;:\&quot;\&quot;,\&quot;MemorySectionName\&quot;:\&quot;\&quot;,\&quot;MemorySectionChecksum\&quot;:\&quot;\&quot;}&quot;,&quot;Constants&quot;:&quot;{\&quot;Name\&quot;:\&quot;Default\&quot;,\&quot;Checksum\&quot;:\&quot;Default\&quot;,\&quot;PerInstancePropertiesChecksum\&quot;:\&quot;\&quot;,\&quot;MemorySectionName\&quot;:\&quot;\&quot;,\&quot;MemorySectionChecksum\&quot;:\&quot;\&quot;}&quot;,&quot;DataTransfers&quot;:&quot;{\&quot;Name\&quot;:\&quot;Default\&quot;,\&quot;Checksum\&quot;:\&quot;Default\&quot;,\&quot;PerInstancePropertiesChecksum\&quot;:\&quot;\&quot;,\&quot;MemorySectionName\&quot;:\&quot;None\&quot;,\&quot;MemorySectionChecksum\&quot;:\&quot;None\&quot;}&quot;,&quot;ModelData&quot;:&quot;{\&quot;Name\&quot;:\&quot;Default\&quot;,\&quot;Checksum\&quot;:\&quot;Default\&quot;,\&quot;PerInstancePropertiesChecksum\&quot;:\&quot;\&quot;,\&quot;MemorySectionName\&quot;:\&quot;None\&quot;,\&quot;MemorySectionChecksum\&quot;:\&quot;None\&quot;}&quot;,&quot;InitializeTerminate&quot;:&quot;{\&quot;Name\&quot;:\&quot;Default\&quot;,\&quot;Checksum\&quot;:\&quot;Default\&quot;,\&quot;PerInstancePropertiesChecksum\&quot;:\&quot;\&quot;,\&quot;MemorySectionName\&quot;:\&quot;\&quot;,\&quot;MemorySectionChecksum\&quot;:\&quot;\&quot;}&quot;,&quot;Execution&quot;:&quot;{\&quot;Name\&quot;:\&quot;Default\&quot;,\&quot;Checksum\&quot;:\&quot;Default\&quot;,\&quot;PerInstancePropertiesChecksum\&quot;:\&quot;\&quot;,\&quot;MemorySectionName\&quot;:\&quot;\&quot;,\&quot;MemorySectionChecksum\&quot;:\&quot;\&quot;}&quot;,&quot;SharedUtility&quot;:&quot;{\&quot;Name\&quot;:\&quot;Default\&quot;,\&quot;Checksum\&quot;:\&quot;Default\&quot;,\&quot;PerInstancePropertiesChecksum\&quot;:\&quot;\&quot;,\&quot;MemorySectionName\&quot;:\&quot;\&quot;,\&quot;MemorySectionChecksum\&quot;:\&quot;\&quot;}&quot;}</defaultsCMapping>
    <globalVariables>CONSTANTS_par</globalVariables>
    <globalVariables>DYN_AERO_par</globalVariables>
    <globalVariables>DYN_ATT_par</globalVariables>
    <globalVariables>DYN_MAG_par</globalVariables>
    <globalVariables>DYN_SC_par</globalVariables>
    <globalVariables>DYN_TRA_par</globalVariables>
    <hasBlockWithPeriodicDiscreteSampleTime>true</hasBlockWithPeriodicDiscreteSampleTime>
    <hasBwsAccessed>true</hasBwsAccessed>
    <hasBwsAccessedByAnyModel>true</hasBwsAccessedByAnyModel>
    <hasContinuousSampleTime>true</hasContinuousSampleTime>
    <hasNonVirtualParameterChangeEvents>true</hasNonVirtualParameterChangeEvents>
    <hasSignalLogging>true</hasSignalLogging>
    <loggingSaveFormat>2</loggingSaveFormat>
    <massMatrixNzMax>13</massMatrixNzMax>
    <maxFreqHz>-1</maxFreqHz>
    <needAbsoluteTimeForNonLoggingPurpose>true</needAbsoluteTimeForNonLoggingPurpose>
    <nonIteratorAssignmentBlock>TST_RWSWV2/DYN/DYN_AERO/ECI Position to LLA/Direction Cosine Matrix ECI to ECEF/Common Time  Calculation/Julian Date Conversion/Assignment</nonIteratorAssignmentBlock>
    <numCStateRecs>4</numCStateRecs>
    <numContinuousStates>13</numContinuousStates>
    <numDStateRecs>12</numDStateRecs>
    <numLoggableCStateRecs>4</numLoggableCStateRecs>
    <numLoggableDStateRecs>12</numLoggableDStateRecs>
    <runtimeNonFcnCallRateInfos type="ModelRefInfoRepo.RateInfo">
      <compiled>true</compiled>
      <needAbsoluteTime>true</needAbsoluteTime>
      <period>0</period>
      <priority>40</priority>
      <rateIdx>0</rateIdx>
    </runtimeNonFcnCallRateInfos>
    <runtimeNonFcnCallRateInfos type="ModelRefInfoRepo.RateInfo">
      <compiled>true</compiled>
      <needAbsoluteTime>true</needAbsoluteTime>
      <nonFcnCallPartitionName>Cont</nonFcnCallPartitionName>
      <period>1</period>
      <priority>40</priority>
      <rateIdx>1</rateIdx>
    </runtimeNonFcnCallRateInfos>
    <sampleTimeInheritanceRule>2</sampleTimeInheritanceRule>
    <timingAndTaskingRegistry>&lt;?xml version=&quot;1.0&quot;?&gt;
&lt;slexec_sto version=&quot;1.1&quot; packageUris=&quot;http://schema.mathworks.com/mf0/slexec_mm_sto/R2019b_201902271317&quot;&gt;
  &lt;sto.Registry type=&quot;sto.Registry&quot; uuid=&quot;976c4724-e45d-4c34-9c92-56f85bd719af&quot;&gt;
    &lt;clocks type=&quot;sto.Timer&quot; uuid=&quot;4611d8c3-eafb-4d94-a911-e44c0350e1e6&quot;&gt;
      &lt;needsToProvideTimeDuringExecution&gt;true&lt;/needsToProvideTimeDuringExecution&gt;
      &lt;clockTickConstraint&gt;PeriodicWithFixedResolution&lt;/clockTickConstraint&gt;
      &lt;resolution&gt;1&lt;/resolution&gt;
      &lt;timeAdvanceMode&gt;FixedStep&lt;/timeAdvanceMode&gt;
      &lt;clockDomain type=&quot;sto.ClockDomain&quot; uuid=&quot;de7e2d94-b15f-4ca2-aad0-cfb3456c49a8&quot;&gt;
        &lt;baseTaskID&gt;_task0&lt;/baseTaskID&gt;
        &lt;computedFundamentalStepSize&gt;1&lt;/computedFundamentalStepSize&gt;
        &lt;rates type=&quot;sto.Rate&quot; uuid=&quot;c820870f-8d4e-48b6-abbe-c72e2647f879&quot;/&gt;
        &lt;rates type=&quot;sto.Rate&quot; uuid=&quot;d1e11201-843d-458a-a188-f34f8990387f&quot;/&gt;
        &lt;rates type=&quot;sto.Rate&quot; uuid=&quot;c7ff14f9-896b-4c92-8579-b0e869cbeda5&quot;/&gt;
        &lt;rootTaskHierarchyElements type=&quot;sto.Task&quot; uuid=&quot;d924b929-9858-42c3-b1f7-a20e0a39bf47&quot;&gt;
          &lt;isExecutable&gt;true&lt;/isExecutable&gt;
          &lt;orderIndex&gt;1&lt;/orderIndex&gt;
          &lt;rates type=&quot;sto.Rate&quot; uuid=&quot;c820870f-8d4e-48b6-abbe-c72e2647f879&quot;&gt;
            &lt;annotation&gt;Cont&lt;/annotation&gt;
            &lt;description&gt;Continuous&lt;/description&gt;
            &lt;eventSourceType&gt;UNSPECIFIED_EVENT_SOURCE&lt;/eventSourceType&gt;
            &lt;registry type=&quot;sto.Registry&quot; uuid=&quot;976c4724-e45d-4c34-9c92-56f85bd719af&quot;/&gt;
            &lt;taskId&gt;_task0&lt;/taskId&gt;
            &lt;rateSpec type=&quot;sto.RateSpec&quot; uuid=&quot;c6acc5f4-0f63-44c7-a124-960c08de17e8&quot;/&gt;
          &lt;/rates&gt;
          &lt;rates type=&quot;sto.Rate&quot; uuid=&quot;d1e11201-843d-458a-a188-f34f8990387f&quot;&gt;
            &lt;annotation&gt;FiM&lt;/annotation&gt;
            &lt;colorIndex&gt;8&lt;/colorIndex&gt;
            &lt;description&gt;Fixed in Minor Step&lt;/description&gt;
            &lt;eventSourceType&gt;UNSPECIFIED_EVENT_SOURCE&lt;/eventSourceType&gt;
            &lt;rateIDX&gt;-1&lt;/rateIDX&gt;
            &lt;registry type=&quot;sto.Registry&quot; uuid=&quot;976c4724-e45d-4c34-9c92-56f85bd719af&quot;/&gt;
            &lt;taskId&gt;_task0&lt;/taskId&gt;
            &lt;useForExecution&gt;NotForExecution&lt;/useForExecution&gt;
            &lt;rateSpec type=&quot;sto.RateSpec&quot; uuid=&quot;e8088abc-49ae-451c-bf98-e9d21e0db901&quot;&gt;
              &lt;offset&gt;1&lt;/offset&gt;
              &lt;rateType&gt;ZOHContinuous&lt;/rateType&gt;
            &lt;/rateSpec&gt;
          &lt;/rates&gt;
          &lt;rates type=&quot;sto.Rate&quot; uuid=&quot;c7ff14f9-896b-4c92-8579-b0e869cbeda5&quot;&gt;
            &lt;annotation&gt;D1&lt;/annotation&gt;
            &lt;colorIndex&gt;2&lt;/colorIndex&gt;
            &lt;description&gt;Discrete 1&lt;/description&gt;
            &lt;eventSourceType&gt;UNSPECIFIED_EVENT_SOURCE&lt;/eventSourceType&gt;
            &lt;rateIDX&gt;1&lt;/rateIDX&gt;
            &lt;registry type=&quot;sto.Registry&quot; uuid=&quot;976c4724-e45d-4c34-9c92-56f85bd719af&quot;/&gt;
            &lt;taskId&gt;_task0&lt;/taskId&gt;
            &lt;rateSpec type=&quot;sto.RateSpec&quot; uuid=&quot;7ab86bc6-8bbd-4ce2-9d66-98bbd4c2fb2a&quot;&gt;
              &lt;period&gt;1&lt;/period&gt;
              &lt;rateType&gt;ClassicPeriodicDiscrete&lt;/rateType&gt;
            &lt;/rateSpec&gt;
          &lt;/rates&gt;
          &lt;elementType&gt;Task&lt;/elementType&gt;
          &lt;identifier&gt;_task0&lt;/identifier&gt;
          &lt;priority&gt;40&lt;/priority&gt;
        &lt;/rootTaskHierarchyElements&gt;
      &lt;/clockDomain&gt;
    &lt;/clocks&gt;
    &lt;clocks type=&quot;sto.Event&quot; uuid=&quot;d4c0ef27-6da4-4f07-85e6-59267a345b10&quot;&gt;
      &lt;eventType&gt;PARAMETER_CHANGE_EVENT&lt;/eventType&gt;
      &lt;cNum&gt;1&lt;/cNum&gt;
      &lt;clockType&gt;Event&lt;/clockType&gt;
      &lt;identifier&gt;ParameterChangeEvent&lt;/identifier&gt;
      &lt;resolution&gt;-1&lt;/resolution&gt;
      &lt;specifiedTaskingMode&gt;ExplicitTasking&lt;/specifiedTaskingMode&gt;
      &lt;timeAdvanceMode&gt;None&lt;/timeAdvanceMode&gt;
      &lt;clockDomain type=&quot;sto.ClockDomain&quot; uuid=&quot;1e2a9158-d92c-4b12-821e-097d30511677&quot;&gt;
        &lt;computedFundamentalStepSize&gt;-1&lt;/computedFundamentalStepSize&gt;
        &lt;rates type=&quot;sto.Rate&quot; uuid=&quot;81b289fd-8319-40b1-8c5a-c53c7173fbb3&quot;/&gt;
        &lt;rootTaskHierarchyElements type=&quot;sto.Task&quot; uuid=&quot;d5e94ecb-5b19-4abb-98ba-2b1306c51abb&quot;&gt;
          &lt;isExecutable&gt;true&lt;/isExecutable&gt;
          &lt;isExplicit&gt;true&lt;/isExplicit&gt;
          &lt;rates type=&quot;sto.Rate&quot; uuid=&quot;81b289fd-8319-40b1-8c5a-c53c7173fbb3&quot;&gt;
            &lt;annotation&gt;Inf&lt;/annotation&gt;
            &lt;colorIndex&gt;6&lt;/colorIndex&gt;
            &lt;description&gt;Constant&lt;/description&gt;
            &lt;eventSourceType&gt;PARAMETER_CHANGE_EVENT&lt;/eventSourceType&gt;
            &lt;rateIDX&gt;2&lt;/rateIDX&gt;
            &lt;registry type=&quot;sto.Registry&quot; uuid=&quot;976c4724-e45d-4c34-9c92-56f85bd719af&quot;/&gt;
            &lt;stringID&gt;ParameterChangeEvent&lt;/stringID&gt;
            &lt;taskId&gt;ModelWideParameterChangeEvent&lt;/taskId&gt;
            &lt;rateSpec type=&quot;sto.RateSpec&quot; uuid=&quot;0bba8782-552e-4375-9bfa-1c5bccf62f3b&quot;&gt;
              &lt;period&gt;inf&lt;/period&gt;
              &lt;rateType&gt;ModelWideParameterChangeEvent&lt;/rateType&gt;
            &lt;/rateSpec&gt;
          &lt;/rates&gt;
          &lt;tNum&gt;1&lt;/tNum&gt;
          &lt;elementType&gt;Task&lt;/elementType&gt;
          &lt;identifier&gt;ModelWideParameterChangeEvent&lt;/identifier&gt;
          &lt;priority&gt;-1&lt;/priority&gt;
          &lt;schedulingClockID&gt;ParameterChangeEvent&lt;/schedulingClockID&gt;
        &lt;/rootTaskHierarchyElements&gt;
      &lt;/clockDomain&gt;
    &lt;/clocks&gt;
    &lt;executionSpec&gt;Undetermined&lt;/executionSpec&gt;
    &lt;hasUnknownEdges&gt;true&lt;/hasUnknownEdges&gt;
    &lt;taskDependencyGraph type=&quot;sto.SerializedTaskConnectionList&quot; uuid=&quot;ac375330-fb60-4e35-a8ba-ccfb22dd4161&quot;&gt;
      &lt;serializedConnectionProperties type=&quot;sto.SerializedConnectionProperties&quot; uuid=&quot;07260161-3fb3-4422-b45e-444f3d07c5ba&quot;&gt;
        &lt;expectedExecOrder&gt;TargetFirst&lt;/expectedExecOrder&gt;
        &lt;targetClockIdentifier&gt;ParameterChangeEvent&lt;/targetClockIdentifier&gt;
        &lt;targetTaskIdentifier&gt;ModelWideParameterChangeEvent&lt;/targetTaskIdentifier&gt;
      &lt;/serializedConnectionProperties&gt;
      &lt;taskIdentifier&gt;_task0&lt;/taskIdentifier&gt;
    &lt;/taskDependencyGraph&gt;
    &lt;taskDependencyGraph type=&quot;sto.SerializedTaskConnectionList&quot; uuid=&quot;94b7bfc2-0c1f-40ce-920c-b89254f685b2&quot;&gt;
      &lt;clockIdentifier&gt;ParameterChangeEvent&lt;/clockIdentifier&gt;
      &lt;serializedConnectionProperties type=&quot;sto.SerializedConnectionProperties&quot; uuid=&quot;a0661ff3-1590-466e-8e18-c57f7aa4d989&quot;&gt;
        &lt;expectedExecOrder&gt;SourceFirst&lt;/expectedExecOrder&gt;
        &lt;targetTaskIdentifier&gt;_task0&lt;/targetTaskIdentifier&gt;
      &lt;/serializedConnectionProperties&gt;
      &lt;taskIdentifier&gt;ModelWideParameterChangeEvent&lt;/taskIdentifier&gt;
    &lt;/taskDependencyGraph&gt;
    &lt;taskPriorityDirection&gt;HighNumberLast&lt;/taskPriorityDirection&gt;
    &lt;tasks type=&quot;sto.Task&quot; uuid=&quot;d924b929-9858-42c3-b1f7-a20e0a39bf47&quot;/&gt;
    &lt;tasks type=&quot;sto.Task&quot; uuid=&quot;d5e94ecb-5b19-4abb-98ba-2b1306c51abb&quot;/&gt;
    &lt;timeAdvanceMode&gt;FixedStep&lt;/timeAdvanceMode&gt;
  &lt;/sto.Registry&gt;
&lt;/slexec_sto&gt;</timingAndTaskingRegistry>
    <FMUBlockMap type="ModelRefInfoRepo.FMUBlockInfo" uuid="21b2b51a-8842-498c-b7a6-ff22d56bcb2c"/>
    <codeGenInfo type="ModelRefInfoRepo.CodeGenInformation" uuid="259724d7-3a77-4b5a-8f67-1f093ad6fddd"/>
    <configSettingsForConsistencyChecks type="ModelRefInfoRepo.ConfigSettingsForConsistencyChecks" uuid="8071d132-ea74-4e5d-9a7b-33f3eabeb8ec">
      <consistentOutportInitialization>true</consistentOutportInitialization>
      <fixedStepSize>1</fixedStepSize>
      <frameDiagnosticSetting>2</frameDiagnosticSetting>
      <hasHybridSampleTime>true</hasHybridSampleTime>
      <signalLoggingSaveFormat>2</signalLoggingSaveFormat>
      <solverName>ode3</solverName>
      <solverType>SOLVER_TYPE_FIXEDSTEP</solverType>
      <hardwareSettings type="ModelRefInfoRepo.HardwareSettings" uuid="932114e5-5fa6-4b5b-9b2f-ca5ad10a0e05">
        <prodBitPerChar>8</prodBitPerChar>
        <prodBitPerDouble>64</prodBitPerDouble>
        <prodBitPerFloat>32</prodBitPerFloat>
        <prodBitPerInt>32</prodBitPerInt>
        <prodBitPerLong>64</prodBitPerLong>
        <prodBitPerLongLong>64</prodBitPerLongLong>
        <prodBitPerPointer>64</prodBitPerPointer>
        <prodBitPerPtrDiffT>64</prodBitPerPtrDiffT>
        <prodBitPerShort>16</prodBitPerShort>
        <prodBitPerSizeT>64</prodBitPerSizeT>
        <prodEndianess>1</prodEndianess>
        <prodLargestAtomicFloat>2</prodLargestAtomicFloat>
        <prodShiftRight>true</prodShiftRight>
        <prodWordSize>64</prodWordSize>
      </hardwareSettings>
    </configSettingsForConsistencyChecks>
    <controllableInputRatesMap type="ModelRefInfoRepo.VarTsUIDMap" uuid="9073498e-1fd9-411e-a82f-b676a15db585"/>
    <controllableOutputRatesMap type="ModelRefInfoRepo.VarTsUIDMap" uuid="8968c0ec-4b45-4cbe-909f-e5237f22a079"/>
    <dataPortGroup type="ModelRefInfoRepo.DataPortGroup" uuid="1e5b1a8b-38fc-4f37-b85f-79634489c2e7"/>
    <interfaceParameterInfo type="ModelRefInfoRepo.InterfaceParameterInfo" uuid="ef5880a9-e492-453c-8ec1-44aceafd002a">
      <globalVariables type="ModelRefInfoRepo.StructureParameter" uuid="b192f98a-8b7b-41a2-afb3-0642a6fc01ff">
        <datatypeChecksum>1703678462</datatypeChecksum>
        <datatypeChecksum>2728046074</datatypeChecksum>
        <datatypeChecksum>2909274786</datatypeChecksum>
        <datatypeChecksum>712723863</datatypeChecksum>
        <datatypeIsAnonymous>true</datatypeIsAnonymous>
        <datatypeName>struct_ZtKgq7qQgrOMpDzzLZ17RD</datatypeName>
        <dimensions>1</dimensions>
        <dimensions>1</dimensions>
        <isUsed>true</isUsed>
        <numDimensions>2</numDimensions>
        <parameterName>DYN_ATT_par</parameterName>
      </globalVariables>
      <globalVariables type="ModelRefInfoRepo.StructureParameter" uuid="3e66bad2-c0ed-408f-b98c-a9800b79c2dd">
        <datatypeChecksum>689760996</datatypeChecksum>
        <datatypeChecksum>478855865</datatypeChecksum>
        <datatypeChecksum>2224477649</datatypeChecksum>
        <datatypeChecksum>2342960373</datatypeChecksum>
        <datatypeIsAnonymous>true</datatypeIsAnonymous>
        <datatypeName>struct_3OptKx60sX28Peciomd4EC</datatypeName>
        <dimensions>1</dimensions>
        <dimensions>1</dimensions>
        <isUsed>true</isUsed>
        <numDimensions>2</numDimensions>
        <parameterName>DYN_SC_par</parameterName>
      </globalVariables>
      <globalVariables type="ModelRefInfoRepo.StructureParameter" uuid="aa72c43b-0170-4d37-96ba-af9cae634a3d">
        <datatypeChecksum>1590574819</datatypeChecksum>
        <datatypeChecksum>534822824</datatypeChecksum>
        <datatypeChecksum>2113521679</datatypeChecksum>
        <datatypeChecksum>473369620</datatypeChecksum>
        <datatypeIsAnonymous>true</datatypeIsAnonymous>
        <datatypeName>struct_zvomUs9swg0LYolfrL6G0F</datatypeName>
        <dimensions>1</dimensions>
        <dimensions>1</dimensions>
        <isUsed>true</isUsed>
        <numDimensions>2</numDimensions>
        <parameterName>CONSTANTS_par</parameterName>
      </globalVariables>
      <globalVariables type="ModelRefInfoRepo.StructureParameter" uuid="1951a803-f933-4036-83f9-711c5eeb09bf">
        <datatypeChecksum>2108705606</datatypeChecksum>
        <datatypeChecksum>4026051633</datatypeChecksum>
        <datatypeChecksum>3536694702</datatypeChecksum>
        <datatypeChecksum>3281040811</datatypeChecksum>
        <datatypeIsAnonymous>true</datatypeIsAnonymous>
        <datatypeName>struct_SSrbxNhDAwveKzBnq5y3AG</datatypeName>
        <dimensions>1</dimensions>
        <dimensions>1</dimensions>
        <isUsed>true</isUsed>
        <numDimensions>2</numDimensions>
        <parameterName>DYN_TRA_par</parameterName>
      </globalVariables>
      <globalVariables type="ModelRefInfoRepo.StructureParameter" uuid="cf985816-6891-4594-a811-3c53e38f13cb">
        <datatypeChecksum>2493588793</datatypeChecksum>
        <datatypeChecksum>3870967105</datatypeChecksum>
        <datatypeChecksum>3768297307</datatypeChecksum>
        <datatypeChecksum>560806328</datatypeChecksum>
        <datatypeIsAnonymous>true</datatypeIsAnonymous>
        <datatypeName>struct_OQVIZ74DlhsweG9NoRv7dB</datatypeName>
        <dimensions>1</dimensions>
        <dimensions>1</dimensions>
        <isUsed>true</isUsed>
        <numDimensions>2</numDimensions>
        <parameterName>DYN_AERO_par</parameterName>
      </globalVariables>
      <globalVariables type="ModelRefInfoRepo.StructureParameter" uuid="fa60f570-5f23-435b-8c69-8e7e390350cb">
        <datatypeChecksum>2118527235</datatypeChecksum>
        <datatypeChecksum>1517501421</datatypeChecksum>
        <datatypeChecksum>1206531461</datatypeChecksum>
        <datatypeChecksum>2017082315</datatypeChecksum>
        <datatypeIsAnonymous>true</datatypeIsAnonymous>
        <datatypeName>struct_XG5FAMxlkIOXT4puaiHssC</datatypeName>
        <dimensions>1</dimensions>
        <dimensions>1</dimensions>
        <isUsed>true</isUsed>
        <numDimensions>2</numDimensions>
        <parameterName>DYN_MAG_par</parameterName>
      </globalVariables>
    </interfaceParameterInfo>
    <messageInfo type="ModelRefInfoRepo.MessageInformation" uuid="f5423751-e42e-46bb-9583-e73cbff689b7"/>
    <methodInfo type="ModelRefInfoRepo.MethodExistenceInfo" uuid="af53f3de-88d9-406a-aedb-0485a557832d">
      <hasDerivMethod>true</hasDerivMethod>
      <hasDisableMethod>true</hasDisableMethod>
      <hasEnableMethod>true</hasEnableMethod>
      <hasForcingFunctionMethod>true</hasForcingFunctionMethod>
      <hasSystemInitializeMethod>true</hasSystemInitializeMethod>
      <hasSystemResetMethod>true</hasSystemResetMethod>
      <hasTerminateMethod>true</hasTerminateMethod>
      <hasUpdateMethod>true</hasUpdateMethod>
    </methodInfo>
    <periodicEventPortUnsupportedBlockInfo type="ModelRefInfoRepo.PeriodicEventPortUnsupportedBlockInfo" uuid="38c5d521-d955-4338-92e1-871e642175ec">
      <multiRateSubsystems>TST_RWSWV2/DYN/DYN_MAG/World Magnetic Model 2015/geomag/Convert from geodetic to  spherical coordinates</multiRateSubsystems>
      <multiRateSubsystems>TST_RWSWV2/DYN/DYN_MAG/World Magnetic Model 2015/geomag/Convert from geodetic to  spherical coordinates </multiRateSubsystems>
    </periodicEventPortUnsupportedBlockInfo>
    <portGroupsRequireSameRate type="ModelRefInfoRepo.PortGroupsRequireSameRate" uuid="9393ed6b-912f-4e6b-b98d-43b9cd22443e">
      <DSMPortGroups type="ModelRefInfoRepo.NameToPortGroupIdxVectMap" uuid="ad0e528a-dffe-4a16-8583-5884387eb4d5"/>
      <GlobalDSMPortGroups type="ModelRefInfoRepo.NameToPortGroupIdxVectMap" uuid="ab1f0845-08b6-485f-8c6a-03805616881d"/>
      <mergedPortGroups type="ModelRefInfoRepo.NameToPortGroupIdxVectMap" uuid="fa499fe7-a6e2-40b1-9b3e-cb5c6015e5aa"/>
    </portGroupsRequireSameRate>
    <rateSpecOfGlobalDSMAccessedByDescExpFcnMdlMap type="ModelRefInfoRepo.GlobalDSMRateSpecMap" uuid="d653a9e5-0133-404d-b63b-3e76f6ed47c0"/>
    <simulinkFunctions type="ModelRefInfoRepo.SimulinkFunctions" uuid="478f1b3c-68a8-4a92-a837-adc9db4288d9">
      <compSimulinkFunctionCatalog></compSimulinkFunctionCatalog>
      <variantSimulinkFunctions type="ModelRefInfoRepo.VariantSimulinkFunctions" uuid="3b4bf932-a1c7-439e-b0f3-fc9f22472deb"/>
    </simulinkFunctions>
    <stateWriterToOwnerMap type="ModelRefInfoRepo.StateWriterInfo" uuid="d5edd779-09c8-476c-aae1-19470e565add"/>
    <stoClientDataRegistry type="sto.ClientDataRegistry" uuid="b280d1c3-6ecf-4147-b24c-24131e82280e">
      <dataSets type="sto.ClientClockNamedDataSet" uuid="d3af1eec-bb92-473d-aedf-3410bf10ac5a">
        <tag>sltpEvents</tag>
      </dataSets>
      <dataSets type="sto.ClientTaskHierarchyElementNamedDataSet" uuid="816abc12-6e03-4af7-86e1-79b4b5b2fef4">
        <tag>sltpTaskGroups</tag>
      </dataSets>
      <dataSets type="sto.ClientTaskHierarchyElementNamedDataSet" uuid="ae43b644-606a-4245-85e7-b9439b961b02">
        <dSet type="ModelRefInfoRepo.SltpTaskData" uuid="02c10d1d-7686-4b3f-b4f2-d621b7c79093"/>
        <tSet type="ModelRefInfoRepo.SltpTaskData" uuid="02c10d1d-7686-4b3f-b4f2-d621b7c79093">
          <dataName>Cont</dataName>
          <linkedSet type="sto.ClientTaskHierarchyElementNamedDataSet" uuid="ae43b644-606a-4245-85e7-b9439b961b02"/>
          <id type="sto.TaskHierarchyElementId">
            <id>_task0</id>
          </id>
        </tSet>
        <tag>sltpTasks</tag>
      </dataSets>
    </stoClientDataRegistry>
    <varTsUIDMap type="ModelRefInfoRepo.VarTsUIDMap" uuid="49921cf5-6e91-4756-8f59-e2c59a40cb8c"/>
  </ModelRefInfoRepo.ModelRefInfoRoot>
</MF0>